comet/PTEmu.py
comet/__init__.py
comet/bispectrum.py
comet/cosmology.py
comet/data.py
comet/grid.py
comet/splines.py
comet/tables.py
comet/data_dir/__init__.py
comet/discreteness/__init__.py
comet/discreteness/find_triangles.cpp
comet/discreteness/grid.cpp
comet/discreteness/grid.h
comet/discreteness/libgrid.so
comet/discreteness/robin_hood.h
comet/discreteness/unique.h
comet_emu-2.1.0.dist-info/licenses/LICENSE
comet_emu-2.1.0.dist-info/METADATA
comet_emu-2.1.0.dist-info/WHEEL
comet_emu-2.1.0.dist-info/top_level.txt
comet_emu-2.1.0.dist-info/RECORD
