Metadata-Version: 2.4
Name: comet-emu
Version: 2.1.0
Summary: COMET - Cosmological Observables Modelled by Emulated perturbation Theory.
Home-page: https://gitlab.com/aegge/comet-emu
Author: Alex Eggemeier, Benjamin Camacho-Quevedo, Andrea Pezzotta, Martin Crocce, Román Scoccimarro, Ariel Sánchez
Author-email: "Alex Eggemeier, Andrea Pezzotta, Benjamin Camacho-Quevedo, Giosue Gambardella, Martin Crocce, Román Scoccimarro, Ariel Sánchez" <aeggemeier@astro.uni-bonn.de>
License: MIT License
Project-URL: Homepage, https://comet-emu.readthedocs.io/
Project-URL: Documentation, https://comet-emu.readthedocs.io/
Project-URL: Repository, https://gitlab.com/aegge/comet-emu
Classifier: Programming Language :: Python :: 3.8
Classifier: License :: OSI Approved :: MIT License
Classifier: Operating System :: OS Independent
Requires-Python: >=3.8
License-File: LICENSE
Requires-Dist: scikit-learn
Requires-Dist: numba
Requires-Dist: numpy
Requires-Dist: matplotlib
Requires-Dist: scipy
Requires-Dist: astropy
Requires-Dist: tqdm
Dynamic: license-file
